sheet/__init__.py
sheet/contents.py
sheet/current_notebook.py
sheet-0.0.5.dist-info/LICENSE
sheet-0.0.5.dist-info/METADATA
sheet-0.0.5.dist-info/WHEEL
sheet-0.0.5.dist-info/top_level.txt
sheet-0.0.5.dist-info/RECORD
