Metadata-Version: 2.1
Name: sheet
Version: 0.0.5
Summary: Tools to extract content from ipython (jupyter) notebooks
Home-page: https://github.com/thorwhalen/sheet
Author: Thor Whalen
License: apache-2.0
Platform: any
Requires-Dist: ipykernel
Requires-Dist: notebook
Requires-Dist: lined
Requires-Dist: grub
Requires-Dist: py2store
